noba/Core.py
noba/__init__.py
noba/app.py
noba/cds.py
noba/clock.py
noba/command.py
noba/confighandler.py
noba/figure.py
noba/optbrowser.py
noba/snippet.py
noba/tab.py
noba/utils.py
noba/version.py
noba/web.py
noba/webapp.py
noba/analyzer_tables/__init__.py
noba/analyzer_tables/annualreturn.py
noba/analyzer_tables/calmar.py
noba/analyzer_tables/drawdown.py
noba/analyzer_tables/leverage.py
noba/analyzer_tables/periodstats.py
noba/analyzer_tables/sharperatio.py
noba/analyzer_tables/sqn.py
noba/analyzer_tables/timereturn.py
noba/analyzer_tables/tradeanalyzers.py
noba/analyzer_tables/tradelist.py
noba/analyzer_tables/transactions.py
noba/analyzer_tables/vwr.py
noba/analyzers/__init__.py
noba/analyzers/plot.py
noba/analyzers/recorder.py
noba/analyzers/tradelist.py
noba/config/config.default.json
noba/config/config.json
noba/dber/__init__.py
noba/dber/_compat.py
noba/dber/_gae.py
noba/dber/_globals.py
noba/dber/_load.py
noba/dber/base.py
noba/dber/connection.py
noba/dber/default_validators.py
noba/dber/drivers.py
noba/dber/exceptions.py
noba/dber/migrator.py
noba/dber/objects.py
noba/dber/restapi.py
noba/dber/utils.py
noba/dber/validators.py
noba/dber/adapters/__init__.py
noba/dber/adapters/base.py
noba/dber/adapters/couchdb.py
noba/dber/adapters/db2.py
noba/dber/adapters/firebird.py
noba/dber/adapters/google.py
noba/dber/adapters/informix.py
noba/dber/adapters/ingres.py
noba/dber/adapters/mongo.py
noba/dber/adapters/mssql.py
noba/dber/adapters/mysql.py
noba/dber/adapters/oracle.py
noba/dber/adapters/postgres.py
noba/dber/adapters/sap.py
noba/dber/adapters/snowflake.py
noba/dber/adapters/sqlite.py
noba/dber/adapters/teradata.py
noba/dber/contrib/__init__.py
noba/dber/contrib/imap_adapter.py
noba/dber/contrib/ipaddress.py
noba/dber/contrib/mockimaplib.py
noba/dber/contrib/ordereddict.py
noba/dber/contrib/portalocker.py
noba/dber/contrib/reserved_sql_keywords.py
noba/dber/dialects/__init__.py
noba/dber/dialects/base.py
noba/dber/dialects/couchdb.py
noba-1.1.7.dist-info/LICENSE
noba-1.1.7.dist-info/METADATA
noba-1.1.7.dist-info/WHEEL
noba-1.1.7.dist-info/entry_points.txt
noba-1.1.7.dist-info/top_level.txt
noba-1.1.7.dist-info/RECORD
